{
  "transitAgency": "ZDZiT Olsztyn",
  "lastUpdateTimestampInMillis": 1633691907,
  "lastUpdateFormatted": "08-10-2021",
  "dataVersion": 1,
  "tramLines": [],
  "busLines": [
    {
      "number": "1",
      "destination": "Wysoka Brama"
    },
    {
      "number": "1",
      "destination": "Kanta"
    },
    {
      "number": "2",
      "destination": "Dworzec Główny"
    },
    {
      "number": "2",
      "destination": "Kanta"
    },
    {
      "number": "3",
      "destination": "Dworzec Główny"
    },
    {
      "number": "3",
      "destination": "Uniwersytet-Prawocheńskiego"
    },
    {
      "number": "101",
      "destination": "Dworzec Główny"
    },
    {
      "number": "101",
      "destination": "Redykajny"
    },
    {
      "number": "103",
      "destination": "Dworzec Główny"
    },
    {
      "number": "103",
      "destination": "Stary Dwór"
    },
    {
      "number": "104",
      "destination": "Cementowa"
    },
    {
      "number": "104",
      "destination": "Klebark Wielki"
    },
    {
      "number": "105",
      "destination": "Borkowskiego"
    },
    {
      "number": "105",
      "destination": "Osiedle Mazurskie"
    },
    {
      "number": "105",
      "destination": "Borkowskiego"
    },
    {
      "number": "105",
      "destination": "Klewki"
    },
    {
      "number": "106",
      "destination": "Cementowa"
    },
    {
      "number": "106",
      "destination": "Gutkowo"
    },
    {
      "number": "106",
      "destination": "Cementowa"
    },
    {
      "number": "106",
      "destination": "Gutkowo"
    },
    {
      "number": "107",
      "destination": "Dajtki"
    },
    {
      "number": "107",
      "destination": "Jakubowo"
    },
    {
      "number": "107",
      "destination": "Łupstych"
    },
    {
      "number": "107",
      "destination": "Jakubowo"
    },
    {
      "number": "108",
      "destination": "Reymonta"
    },
    {
      "number": "108",
      "destination": "Dworzec Główny"
    },
    {
      "number": "109",
      "destination": "Osiedle Podleśna"
    },
    {
      "number": "109",
      "destination": "Słoneczny Stok"
    },
    {
      "number": "110",
      "destination": "Polmozbyt"
    },
    {
      "number": "110",
      "destination": "Jakubowo"
    },
    {
      "number": "110",
      "destination": "Polmozbyt"
    },
    {
      "number": "110",
      "destination": "Spręcowo"
    },
    {
      "number": "110",
      "destination": "Polmozbyt"
    },
    {
      "number": "110",
      "destination": "Jakubowo"
    },
    {
      "number": "111",
      "destination": "Nagórki"
    },
    {
      "number": "111",
      "destination": "Gutkowo"
    },
    {
      "number": "112",
      "destination": "Reymonta"
    },
    {
      "number": "112",
      "destination": "Dworzec Główny"
    },
    {
      "number": "112",
      "destination": "Reymonta"
    },
    {
      "number": "113",
      "destination": "Panasa"
    },
    {
      "number": "113",
      "destination": "Dajtki"
    },
    {
      "number": "114",
      "destination": "Dworzec Główny"
    },
    {
      "number": "114",
      "destination": "Barczewo"
    },
    {
      "number": "116",
      "destination": "Osiedle Mazurskie"
    },
    {
      "number": "116",
      "destination": "Track"
    },
    {
      "number": "116",
      "destination": "Osiedle Mazurskie"
    },
    {
      "number": "117",
      "destination": "Osiedle Generałów"
    },
    {
      "number": "117",
      "destination": "Cmentarz Dywity-Brama Wschodnia"
    },
    {
      "number": "120",
      "destination": "Panasa"
    },
    {
      "number": "120",
      "destination": "Dworzec Główny"
    },
    {
      "number": "121",
      "destination": "Bartąska-Rondo"
    },
    {
      "number": "121",
      "destination": "Cementowa"
    },
    {
      "number": "124",
      "destination": "Dworzec Główny"
    },
    {
      "number": "124",
      "destination": "Barczewo"
    },
    {
      "number": "126",
      "destination": "Osiedle Generałów"
    },
    {
      "number": "126",
      "destination": "Jagiellońska-Ogrody"
    },
    {
      "number": "127",
      "destination": "Witosa"
    },
    {
      "number": "127",
      "destination": "Redykajny"
    },
    {
      "number": "128",
      "destination": "Brzeziny"
    },
    {
      "number": "128",
      "destination": "Dworzec Główny"
    },
    {
      "number": "128",
      "destination": "Brzeziny"
    },
    {
      "number": "128",
      "destination": "Cementowa"
    },
    {
      "number": "128",
      "destination": "Brzeziny"
    },
    {
      "number": "128",
      "destination": "Uniwersytet-Centrum Konferencyjne"
    },
    {
      "number": "129",
      "destination": "Plac Roosevelta"
    },
    {
      "number": "129",
      "destination": "Olsztynek"
    },
    {
      "number": "130",
      "destination": "Panasa"
    },
    {
      "number": "130",
      "destination": "Stary Dwór"
    },
    {
      "number": "131",
      "destination": "Panasa"
    },
    {
      "number": "131",
      "destination": "Indykpol"
    },
    {
      "number": "136",
      "destination": "Bartąska-Rondo"
    },
    {
      "number": "136",
      "destination": "Jagiellońska-Szpital"
    },
    {
      "number": "141",
      "destination": "Osiedle Generałów"
    },
    {
      "number": "141",
      "destination": "Cementowa"
    },
    {
      "number": "201",
      "destination": "Kutrzeby"
    },
    {
      "number": "202",
      "destination": "Pieczewo"
    },
    {
      "number": "203",
      "destination": "Andersa"
    },
    {
      "number": "204",
      "destination": "Andersa"
    },
    {
      "number": "205",
      "destination": "Tęczowy Las"
    },
    {
      "number": "205",
      "destination": "Galeria Warmińska"
    },
    {
      "number": "302",
      "destination": "Dajtki"
    },
    {
      "number": "302",
      "destination": "Stary Dwór"
    },
    {
      "number": "303",
      "destination": "Witosa"
    },
    {
      "number": "303",
      "destination": "Stary Dwór"
    },
    {
      "number": "304",
      "destination": "Dworzec Główny"
    },
    {
      "number": "304",
      "destination": "Wójtowo-Leszczynowa"
    },
    {
      "number": "305",
      "destination": "Dworzec Główny"
    },
    {
      "number": "305",
      "destination": "Stary Dwór"
    },
    {
      "number": "307",
      "destination": "Witosa"
    },
    {
      "number": "307",
      "destination": "Plaża Miejska"
    },
    {
      "number": "309",
      "destination": "Jakubowo"
    },
    {
      "number": "309",
      "destination": "Stary Dwór"
    },
    {
      "number": "N01",
      "destination": "Dworzec Główny"
    },
    {
      "number": "N02",
      "destination": "Dworzec Główny"
    },
    {
      "number": "Z-3",
      "destination": "Dworzec Główny"
    },
    {
      "number": "Z-3",
      "destination": "Uniwersytet-Prawocheńskiego"
    },
    {
      "number": "Z13",
      "destination": "Gębika"
    },
    {
      "number": "Z13",
      "destination": "Krasickiego-Wilczyńskiego"
    }
  ],
  "tramStops": [],
  "busStops": [
    {
      "stopName": "Pstrowskiego-Sikorskiego",
      "stopLines": [
        "1",
        "2",
        "3",
        "103",
        "127",
        "Z-3"
      ]
    },
    {
      "stopName": "Andersa",
      "stopLines": [
        "1",
        "2",
        "127",
        "130",
        "131",
        "136",
        "203",
        "204",
        "303",
        "307",
        "N01"
      ]
    },
    {
      "stopName": "Centrum",
      "stopLines": [
        "1",
        "101",
        "105",
        "106",
        "107",
        "109",
        "110",
        "111",
        "113",
        "117",
        "120",
        "128",
        "N01"
      ]
    },
    {
      "stopName": "Dywizjonu 303",
      "stopLines": [
        "1",
        "2",
        "3",
        "127",
        "Z-3"
      ]
    },
    {
      "stopName": "Auchan",
      "stopLines": [
        "1",
        "2",
        "127",
        "130",
        "131",
        "136",
        "303",
        "307"
      ]
    },
    {
      "stopName": "Sikorskiego-Wilczyńskiego",
      "stopLines": [
        "1",
        "2",
        "117",
        "121",
        "126",
        "127",
        "130",
        "131",
        "136",
        "141",
        "203",
        "303",
        "307",
        "N01"
      ]
    },
    {
      "stopName": "Skwer Wakara",
      "stopLines": [
        "1",
        "2",
        "3",
        "105",
        "106",
        "107",
        "111",
        "113",
        "117",
        "120",
        "128",
        "N01",
        "Z-3"
      ]
    },
    {
      "stopName": "Wysoka Brama",
      "stopLines": [
        "1",
        "101",
        "105",
        "107",
        "109",
        "111",
        "113",
        "116",
        "128",
        "136",
        "309",
        "N01",
        "N02"
      ]
    },
    {
      "stopName": "Płoskiego",
      "stopLines": [
        "1",
        "2",
        "121",
        "205"
      ]
    },
    {
      "stopName": "Witosa",
      "stopLines": [
        "1",
        "2",
        "127",
        "205",
        "303",
        "307"
      ]
    },
    {
      "stopName": "Galeria Warmińska",
      "stopLines": [
        "1",
        "2",
        "3",
        "111",
        "121",
        "127",
        "130",
        "131",
        "136",
        "205",
        "303",
        "305",
        "307",
        "N01",
        "Z-3"
      ]
    },
    {
      "stopName": "Kanta",
      "stopLines": [
        "1",
        "2",
        "127",
        "205",
        "303",
        "307"
      ]
    },
    {
      "stopName": "Szpital Wojewódzki",
      "stopLines": [
        "1",
        "2",
        "3",
        "105",
        "106",
        "107",
        "111",
        "113",
        "116",
        "117",
        "120",
        "128",
        "N01",
        "Z-3"
      ]
    },
    {
      "stopName": "Dworzec Główny",
      "stopLines": [
        "2",
        "3",
        "101",
        "103",
        "107",
        "108",
        "112",
        "114",
        "120",
        "121",
        "124",
        "126",
        "128",
        "131",
        "304",
        "305",
        "N01",
        "N02",
        "Z-3"
      ]
    },
    {
      "stopName": "Filharmonia",
      "stopLines": [
        "2",
        "3",
        "109",
        "Z-3"
      ]
    },
    {
      "stopName": "Kętrzyńskiego",
      "stopLines": [
        "2",
        "3",
        "Z-3"
      ]
    },
    {
      "stopName": "Uniwersytet-Prawocheńskiego",
      "stopLines": [
        "3",
        "103",
        "109",
        "129",
        "130",
        "136",
        "302",
        "303",
        "305",
        "307",
        "309",
        "N01",
        "N02",
        "Z-3"
      ]
    },
    {
      "stopName": "Pozorty",
      "stopLines": [
        "3",
        "128",
        "130",
        "136",
        "303",
        "305",
        "307",
        "N01",
        "Z-3"
      ]
    },
    {
      "stopName": "Uniwersytet-Pływalnia",
      "stopLines": [
        "3",
        "128",
        "130",
        "136",
        "303",
        "305",
        "307",
        "N01",
        "Z-3"
      ]
    },
    {
      "stopName": "Seminarium Hosianum",
      "stopLines": [
        "101",
        "127"
      ]
    },
    {
      "stopName": "Św. Arnolda",
      "stopLines": [
        "101",
        "127"
      ]
    },
    {
      "stopName": "Redykajny",
      "stopLines": [
        "101",
        "127"
      ]
    },
    {
      "stopName": "Narcyzowa",
      "stopLines": [
        "101",
        "127"
      ]
    },
    {
      "stopName": "Plac Pułaskiego",
      "stopLines": [
        "101",
        "109"
      ]
    },
    {
      "stopName": "Grabowa",
      "stopLines": [
        "101",
        "106",
        "111",
        "127",
        "N02"
      ]
    },
    {
      "stopName": "Mickiewicza",
      "stopLines": [
        "101"
      ]
    },
    {
      "stopName": "Św. Wojciecha",
      "stopLines": [
        "101",
        "105",
        "107",
        "109",
        "111",
        "113",
        "116",
        "128",
        "136",
        "309",
        "N01",
        "N02"
      ]
    },
    {
      "stopName": "Kajki",
      "stopLines": [
        "101",
        "109",
        "116",
        "120",
        "309",
        "N02"
      ]
    },
    {
      "stopName": "Jeziorna",
      "stopLines": [
        "101",
        "106",
        "111",
        "127",
        "N02"
      ]
    },
    {
      "stopName": "Jezioro Długie",
      "stopLines": [
        "101",
        "106",
        "111",
        "127",
        "N02"
      ]
    },
    {
      "stopName": "Jemioły",
      "stopLines": [
        "101",
        "127"
      ]
    },
    {
      "stopName": "Likusy",
      "stopLines": [
        "101",
        "106",
        "111",
        "127",
        "N02"
      ]
    },
    {
      "stopName": "Plac Bema",
      "stopLines": [
        "101",
        "109",
        "116",
        "120",
        "309",
        "N02"
      ]
    },
    {
      "stopName": "Grunwaldzka",
      "stopLines": [
        "101",
        "107",
        "111",
        "127",
        "N02"
      ]
    },
    {
      "stopName": "Plac Roosevelta",
      "stopLines": [
        "101",
        "103",
        "105",
        "107",
        "109",
        "111",
        "113",
        "116",
        "127",
        "128",
        "129",
        "136",
        "309",
        "N01",
        "N02"
      ]
    },
    {
      "stopName": "Zespół Szkół Ekonomicznych",
      "stopLines": [
        "101",
        "106",
        "111",
        "127",
        "N02"
      ]
    },
    {
      "stopName": "Letniskowa",
      "stopLines": [
        "101",
        "106",
        "111",
        "127",
        "N02"
      ]
    },
    {
      "stopName": "Żbicza",
      "stopLines": [
        "101",
        "127"
      ]
    },
    {
      "stopName": "Targowisko Miejskie",
      "stopLines": [
        "101",
        "107",
        "111",
        "127",
        "N02"
      ]
    },
    {
      "stopName": "Wędkarska",
      "stopLines": [
        "101",
        "106",
        "111",
        "127",
        "N02"
      ]
    },
    {
      "stopName": "Osiedle Podgrodzie",
      "stopLines": [
        "103",
        "109",
        "113",
        "128",
        "129",
        "136",
        "309",
        "N01",
        "N02"
      ]
    },
    {
      "stopName": "Uniwersytet-Rektorat",
      "stopLines": [
        "103",
        "109",
        "129",
        "136",
        "302",
        "307",
        "309",
        "N01",
        "N02"
      ]
    },
    {
      "stopName": "Straż Pożarna",
      "stopLines": [
        "103",
        "116",
        "127"
      ]
    },
    {
      "stopName": "Stary Dwór",
      "stopLines": [
        "103",
        "128",
        "130",
        "302",
        "303",
        "305",
        "309"
      ]
    },
    {
      "stopName": "Szpital Miejski",
      "stopLines": [
        "103",
        "116",
        "127"
      ]
    },
    {
      "stopName": "Armii Krajowej",
      "stopLines": [
        "103",
        "109",
        "113",
        "128",
        "129",
        "136",
        "309",
        "N01",
        "N02"
      ]
    },
    {
      "stopName": "Kołobrzeska",
      "stopLines": [
        "103",
        "106",
        "107",
        "121",
        "126",
        "128",
        "131",
        "305",
        "N01"
      ]
    },
    {
      "stopName": "Pstrowskiego-Dworcowa",
      "stopLines": [
        "103",
        "120"
      ]
    },
    {
      "stopName": "Uniwersytet-Centrum Konferencyjne",
      "stopLines": [
        "103",
        "109",
        "128",
        "130",
        "302",
        "303",
        "305",
        "309",
        "N02"
      ]
    },
    {
      "stopName": "Szpital Dziecięcy",
      "stopLines": [
        "103",
        "105",
        "106",
        "107",
        "111",
        "113",
        "116",
        "117",
        "120",
        "128",
        "131",
        "N01"
      ]
    },
    {
      "stopName": "Uniwersytet-Świetlista",
      "stopLines": [
        "103",
        "109",
        "128",
        "130",
        "302",
        "303",
        "305",
        "309",
        "N02"
      ]
    },
    {
      "stopName": "Dworcowa-Przychodnia",
      "stopLines": [
        "103",
        "106",
        "107",
        "121",
        "126",
        "128",
        "131",
        "305",
        "N01"
      ]
    },
    {
      "stopName": "Uniwersytet-Słoneczna",
      "stopLines": [
        "103",
        "109",
        "128",
        "130",
        "302",
        "303",
        "305",
        "309",
        "N02"
      ]
    },
    {
      "stopName": "Uniwersytet-Stadion",
      "stopLines": [
        "103",
        "109",
        "129",
        "130",
        "302",
        "303",
        "305",
        "309",
        "N02"
      ]
    },
    {
      "stopName": "Plac Inwalidów Wojennych",
      "stopLines": [
        "103",
        "105",
        "106",
        "107",
        "113",
        "128",
        "131",
        "N01"
      ]
    },
    {
      "stopName": "Klebark Mały II",
      "stopLines": [
        "104"
      ]
    },
    {
      "stopName": "Klebark Wielki",
      "stopLines": [
        "104"
      ]
    },
    {
      "stopName": "Tor motocrossowy",
      "stopLines": [
        "104",
        "304"
      ]
    },
    {
      "stopName": "Klebark Mały-Zapałowo",
      "stopLines": [
        "104"
      ]
    },
    {
      "stopName": "Cementowa",
      "stopLines": [
        "104",
        "106",
        "121",
        "128",
        "141",
        "304"
      ]
    },
    {
      "stopName": "Klebark Mały I",
      "stopLines": [
        "104",
        "304"
      ]
    },
    {
      "stopName": "Klebark Mały-Kolonia",
      "stopLines": [
        "104"
      ]
    },
    {
      "stopName": "Klewki",
      "stopLines": [
        "105"
      ]
    },
    {
      "stopName": "Osiedle Mazurskie",
      "stopLines": [
        "105",
        "116"
      ]
    },
    {
      "stopName": "Jezioro Skanda",
      "stopLines": [
        "105"
      ]
    },
    {
      "stopName": "Szczęsne I",
      "stopLines": [
        "105"
      ]
    },
    {
      "stopName": "Pstrowskiego",
      "stopLines": [
        "105",
        "111",
        "113",
        "116",
        "117",
        "121",
        "126",
        "131",
        "141",
        "305"
      ]
    },
    {
      "stopName": "Gdyńska",
      "stopLines": [
        "105",
        "116"
      ]
    },
    {
      "stopName": "Graniczna",
      "stopLines": [
        "105"
      ]
    },
    {
      "stopName": "Piękna Góra",
      "stopLines": [
        "105"
      ]
    },
    {
      "stopName": "Szczęsne II",
      "stopLines": [
        "105"
      ]
    },
    {
      "stopName": "Osińskiego",
      "stopLines": [
        "105"
      ]
    },
    {
      "stopName": "Stadion Stomil",
      "stopLines": [
        "105",
        "113",
        "121",
        "126",
        "305"
      ]
    },
    {
      "stopName": " SZCZEGÓŁY",
      "stopLines": [
        "105",
        "106",
        "110",
        "113",
        "117",
        "120",
        "121",
        "126",
        "128",
        "129",
        "130",
        "131",
        "141",
        "205",
        "N01",
        "Z13"
      ]
    },
    {
      "stopName": "Piłsudskiego",
      "stopLines": [
        "105",
        "113",
        "121",
        "126",
        "141",
        "305"
      ]
    },
    {
      "stopName": "Barczewskiego",
      "stopLines": [
        "105"
      ]
    },
    {
      "stopName": "Borkowskiego",
      "stopLines": [
        "105"
      ]
    },
    {
      "stopName": "Wojewódzki Ośrodek Ruchu Drogowego",
      "stopLines": [
        "106",
        "114",
        "304"
      ]
    },
    {
      "stopName": "Bohaterów Monte Cassino",
      "stopLines": [
        "106"
      ]
    },
    {
      "stopName": "Składowa",
      "stopLines": [
        "106",
        "114",
        "121",
        "141",
        "304"
      ]
    },
    {
      "stopName": "Żurawia",
      "stopLines": [
        "106",
        "111",
        "N02"
      ]
    },
    {
      "stopName": "Poranna",
      "stopLines": [
        "106",
        "111",
        "N02"
      ]
    },
    {
      "stopName": "Teatr im. S. Jaracza",
      "stopLines": [
        "106",
        "110",
        "116",
        "117",
        "120",
        "136",
        "309",
        "N02"
      ]
    },
    {
      "stopName": "Sokola",
      "stopLines": [
        "106",
        "111",
        "N02"
      ]
    },
    {
      "stopName": "Tor Kartingowy",
      "stopLines": [
        "106"
      ]
    },
    {
      "stopName": "Olsztyńskie Zakłady Graficzne",
      "stopLines": [
        "106",
        "114",
        "121",
        "304"
      ]
    },
    {
      "stopName": "Kanarkowa",
      "stopLines": [
        "106",
        "111",
        "N02"
      ]
    },
    {
      "stopName": "Sprzętowa",
      "stopLines": [
        "106"
      ]
    },
    {
      "stopName": "Wioślarska",
      "stopLines": [
        "106",
        "111",
        "N02"
      ]
    },
    {
      "stopName": "Obi",
      "stopLines": [
        "106",
        "114",
        "121",
        "141",
        "304"
      ]
    },
    {
      "stopName": "Towarowa-Budowlana",
      "stopLines": [
        "106",
        "114",
        "304"
      ]
    },
    {
      "stopName": "Zakład Gazowniczy",
      "stopLines": [
        "106",
        "121",
        "128",
        "141",
        "304"
      ]
    },
    {
      "stopName": "Gutkowo",
      "stopLines": [
        "106",
        "111",
        "N02"
      ]
    },
    {
      "stopName": "Dworzec Zachodni",
      "stopLines": [
        "106"
      ]
    },
    {
      "stopName": "Stacja Krwiodawstwa",
      "stopLines": [
        "107",
        "309",
        "N02"
      ]
    },
    {
      "stopName": "Kudypy-Leśne Arboretum",
      "stopLines": [
        "107"
      ]
    },
    {
      "stopName": "Jakubowo",
      "stopLines": [
        "107",
        "110",
        "117",
        "309"
      ]
    },
    {
      "stopName": "Zatoka Miła",
      "stopLines": [
        "107",
        "113",
        "302",
        "307",
        "N02"
      ]
    },
    {
      "stopName": "Perkoza",
      "stopLines": [
        "107"
      ]
    },
    {
      "stopName": "Okrągła",
      "stopLines": [
        "107",
        "113",
        "302",
        "N02"
      ]
    },
    {
      "stopName": "Plaża Miejska",
      "stopLines": [
        "107",
        "113",
        "302",
        "307",
        "N02"
      ]
    },
    {
      "stopName": "Dożynkowa",
      "stopLines": [
        "107",
        "113",
        "302",
        "N02"
      ]
    },
    {
      "stopName": "Limanowskiego",
      "stopLines": [
        "107",
        "108",
        "109",
        "112",
        "116",
        "124",
        "126",
        "131",
        "309",
        "N02"
      ]
    },
    {
      "stopName": "Kłosowa",
      "stopLines": [
        "107",
        "113",
        "302",
        "N02"
      ]
    },
    {
      "stopName": "Owocowa",
      "stopLines": [
        "107",
        "113",
        "302",
        "N02"
      ]
    },
    {
      "stopName": "Żytnia-Szkoła",
      "stopLines": [
        "107",
        "113",
        "302",
        "N02"
      ]
    },
    {
      "stopName": "Łupstych",
      "stopLines": [
        "107"
      ]
    },
    {
      "stopName": "Dajtki",
      "stopLines": [
        "107",
        "113",
        "302",
        "N02"
      ]
    },
    {
      "stopName": "Szpital MSWiA",
      "stopLines": [
        "107",
        "110",
        "117",
        "309",
        "N02"
      ]
    },
    {
      "stopName": "Rolna",
      "stopLines": [
        "107",
        "113",
        "302",
        "N02"
      ]
    },
    {
      "stopName": "Borowa",
      "stopLines": [
        "108",
        "109",
        "112",
        "126",
        "136"
      ]
    },
    {
      "stopName": "Reymonta",
      "stopLines": [
        "108",
        "112",
        "116"
      ]
    },
    {
      "stopName": "Słupy-Kościół",
      "stopLines": [
        "108",
        "112"
      ]
    },
    {
      "stopName": "Dywity",
      "stopLines": [
        "108",
        "110",
        "112"
      ]
    },
    {
      "stopName": "Słupy",
      "stopLines": [
        "108",
        "112"
      ]
    },
    {
      "stopName": "Dywity-Grzybowa",
      "stopLines": [
        "108",
        "110",
        "112"
      ]
    },
    {
      "stopName": "Myki-Ogrody I",
      "stopLines": [
        "108",
        "112"
      ]
    },
    {
      "stopName": "Cmentarz Dywity-Brama Zachodnia",
      "stopLines": [
        "108",
        "110",
        "112",
        "117"
      ]
    },
    {
      "stopName": "Wadąg",
      "stopLines": [
        "108",
        "112"
      ]
    },
    {
      "stopName": "Dywity-Cefarm",
      "stopLines": [
        "108",
        "112"
      ]
    },
    {
      "stopName": "Słupy-Osiedle Leśne",
      "stopLines": [
        "108",
        "112"
      ]
    },
    {
      "stopName": "Kieźliny-Przedszkole",
      "stopLines": [
        "108",
        "112"
      ]
    },
    {
      "stopName": "Kieźliny-Kościół",
      "stopLines": [
        "108",
        "112"
      ]
    },
    {
      "stopName": "Różnowo-Kolonia",
      "stopLines": [
        "108",
        "112"
      ]
    },
    {
      "stopName": "Ośrodek Doradztwa Rolniczego",
      "stopLines": [
        "108",
        "112",
        "126"
      ]
    },
    {
      "stopName": "Wrocławska",
      "stopLines": [
        "108",
        "109",
        "112",
        "124",
        "126",
        "131",
        "136"
      ]
    },
    {
      "stopName": "Myki-Ogrody II",
      "stopLines": [
        "108",
        "112"
      ]
    },
    {
      "stopName": "Różnowo-Osiedle",
      "stopLines": [
        "108",
        "112"
      ]
    },
    {
      "stopName": "Jagiellońska-Ogrody",
      "stopLines": [
        "108",
        "112",
        "126"
      ]
    },
    {
      "stopName": "Kieźliny-Domagały Kapliczka",
      "stopLines": [
        "108",
        "112"
      ]
    },
    {
      "stopName": "Bydgoska",
      "stopLines": [
        "108",
        "109",
        "112",
        "126",
        "136"
      ]
    },
    {
      "stopName": "Różnowo",
      "stopLines": [
        "108",
        "112"
      ]
    },
    {
      "stopName": "Szewczenki",
      "stopLines": [
        "108",
        "109",
        "112",
        "124",
        "126",
        "131",
        "136"
      ]
    },
    {
      "stopName": "Różnowo Stare",
      "stopLines": [
        "108",
        "112"
      ]
    },
    {
      "stopName": "Dywity-Gminny Ośrodek Kultury",
      "stopLines": [
        "108",
        "110",
        "112"
      ]
    },
    {
      "stopName": "Jagiellońska-Szpital",
      "stopLines": [
        "108",
        "112",
        "126",
        "136"
      ]
    },
    {
      "stopName": "Cmentarz Dywity-Brama Wschodnia",
      "stopLines": [
        "108",
        "112",
        "117"
      ]
    },
    {
      "stopName": "Cmentarz Poprzeczna",
      "stopLines": [
        "108",
        "112",
        "116",
        "124",
        "131"
      ]
    },
    {
      "stopName": "Osiedle Podleśna",
      "stopLines": [
        "109"
      ]
    },
    {
      "stopName": "Słoneczny Stok",
      "stopLines": [
        "109",
        "N02"
      ]
    },
    {
      "stopName": "Soplicy",
      "stopLines": [
        "110",
        "121"
      ]
    },
    {
      "stopName": "Park Naukowo-Technologiczny - BK",
      "stopLines": [
        "110"
      ]
    },
    {
      "stopName": "Michelin-Biuro",
      "stopLines": [
        "110",
        "141"
      ]
    },
    {
      "stopName": "Michelin-Brama nr 6",
      "stopLines": [
        "110",
        "141"
      ]
    },
    {
      "stopName": "Zespół Szkół Samochodowych",
      "stopLines": [
        "110",
        "117",
        "N02"
      ]
    },
    {
      "stopName": "Spręcowo",
      "stopLines": [
        "110"
      ]
    },
    {
      "stopName": "Las Miejski",
      "stopLines": [
        "110",
        "117"
      ]
    },
    {
      "stopName": "Rejewskiego",
      "stopLines": [
        "110"
      ]
    },
    {
      "stopName": "Teatr Lalek",
      "stopLines": [
        "110"
      ]
    },
    {
      "stopName": "Westerplatte",
      "stopLines": [
        "110"
      ]
    },
    {
      "stopName": "Radiowa",
      "stopLines": [
        "110",
        "117",
        "N02"
      ]
    },
    {
      "stopName": "Zajezdnia MPK",
      "stopLines": [
        "110",
        "121",
        "141"
      ]
    },
    {
      "stopName": "Wyspiańskiego",
      "stopLines": [
        "110",
        "117",
        "136",
        "N02"
      ]
    },
    {
      "stopName": "Park Naukowo-Technologiczny - B1",
      "stopLines": [
        "110"
      ]
    },
    {
      "stopName": "Michelin-Brama nr 3",
      "stopLines": [
        "110"
      ]
    },
    {
      "stopName": "Ługwałd DK51",
      "stopLines": [
        "110"
      ]
    },
    {
      "stopName": "Spręcowo-Klasztor",
      "stopLines": [
        "110"
      ]
    },
    {
      "stopName": "Dywity-Olsztyńska",
      "stopLines": [
        "110"
      ]
    },
    {
      "stopName": "Spręcowo-Świetlica",
      "stopLines": [
        "110"
      ]
    },
    {
      "stopName": "Polmozbyt",
      "stopLines": [
        "110"
      ]
    },
    {
      "stopName": "Park Naukowo-Technologiczny - L2",
      "stopLines": [
        "110"
      ]
    },
    {
      "stopName": "Paukszty",
      "stopLines": [
        "111",
        "121",
        "205",
        "N01"
      ]
    },
    {
      "stopName": "Orłowicza",
      "stopLines": [
        "111",
        "121",
        "205",
        "N01"
      ]
    },
    {
      "stopName": "Synów Pułku-Ogrody",
      "stopLines": [
        "111",
        "121",
        "131",
        "205",
        "305"
      ]
    },
    {
      "stopName": "Dom Kultury Agora",
      "stopLines": [
        "111",
        "116",
        "117",
        "131"
      ]
    },
    {
      "stopName": "Nagórki",
      "stopLines": [
        "111",
        "121",
        "205",
        "N01"
      ]
    },
    {
      "stopName": "Synów Pułku",
      "stopLines": [
        "111",
        "113",
        "117",
        "120",
        "121",
        "126",
        "131",
        "141",
        "305"
      ]
    },
    {
      "stopName": "Panasa",
      "stopLines": [
        "113",
        "120",
        "127",
        "130",
        "131",
        "205",
        "303",
        "307",
        "N01"
      ]
    },
    {
      "stopName": "Saperska",
      "stopLines": [
        "113",
        "302",
        "307",
        "N02"
      ]
    },
    {
      "stopName": "Boenigka",
      "stopLines": [
        "113",
        "117",
        "120",
        "121",
        "126",
        "141",
        "205",
        "N01"
      ]
    },
    {
      "stopName": "Jagiellończyka",
      "stopLines": [
        "113",
        "302",
        "307",
        "N02"
      ]
    },
    {
      "stopName": "Carrefour",
      "stopLines": [
        "113",
        "117",
        "120",
        "121",
        "126",
        "141",
        "205",
        "N01"
      ]
    },
    {
      "stopName": "Wańkowicza",
      "stopLines": [
        "113",
        "117",
        "120",
        "126",
        "141"
      ]
    },
    {
      "stopName": "Kaplityny-Północ",
      "stopLines": [
        "114"
      ]
    },
    {
      "stopName": "Barczewo-Warmińska",
      "stopLines": [
        "114",
        "124"
      ]
    },
    {
      "stopName": "Wójtowo-Leszczynowa",
      "stopLines": [
        "114",
        "304"
      ]
    },
    {
      "stopName": "Wrócikowo",
      "stopLines": [
        "114",
        "124"
      ]
    },
    {
      "stopName": "Towarowa-Cementowa",
      "stopLines": [
        "114"
      ]
    },
    {
      "stopName": "Barczewo-Pętla",
      "stopLines": [
        "114",
        "124"
      ]
    },
    {
      "stopName": "Barczewo-Szkoła",
      "stopLines": [
        "114",
        "124"
      ]
    },
    {
      "stopName": "Wójtowo",
      "stopLines": [
        "114",
        "304"
      ]
    },
    {
      "stopName": "Barczewo-Miła",
      "stopLines": [
        "114",
        "124"
      ]
    },
    {
      "stopName": "Barczewo",
      "stopLines": [
        "114",
        "124"
      ]
    },
    {
      "stopName": "Wójtowo-Fabryka",
      "stopLines": [
        "114"
      ]
    },
    {
      "stopName": "Kaplityny-Południe",
      "stopLines": [
        "114"
      ]
    },
    {
      "stopName": "Łęgajny-Pętla",
      "stopLines": [
        "114",
        "124"
      ]
    },
    {
      "stopName": "Indykpol",
      "stopLines": [
        "116",
        "131"
      ]
    },
    {
      "stopName": "Niepodległości",
      "stopLines": [
        "116"
      ]
    },
    {
      "stopName": "Track",
      "stopLines": [
        "116"
      ]
    },
    {
      "stopName": "Sienkiewicza",
      "stopLines": [
        "116"
      ]
    },
    {
      "stopName": "Samulowskiego",
      "stopLines": [
        "116",
        "120",
        "309",
        "N02"
      ]
    },
    {
      "stopName": "Żeromskiego",
      "stopLines": [
        "116",
        "136"
      ]
    },
    {
      "stopName": "Kossaka",
      "stopLines": [
        "116"
      ]
    },
    {
      "stopName": "Paderewskiego",
      "stopLines": [
        "116"
      ]
    },
    {
      "stopName": "Zielona Górka",
      "stopLines": [
        "116",
        "124",
        "131"
      ]
    },
    {
      "stopName": "Karolin",
      "stopLines": [
        "116",
        "124",
        "131"
      ]
    },
    {
      "stopName": "Morwowa",
      "stopLines": [
        "116",
        "124",
        "131"
      ]
    },
    {
      "stopName": "Puszkina",
      "stopLines": [
        "116",
        "136"
      ]
    },
    {
      "stopName": "Emilii Plater",
      "stopLines": [
        "116"
      ]
    },
    {
      "stopName": "Indykpol-Biuro",
      "stopLines": [
        "116",
        "131"
      ]
    },
    {
      "stopName": "Zalbki",
      "stopLines": [
        "116",
        "124",
        "131"
      ]
    },
    {
      "stopName": "Tracka",
      "stopLines": [
        "116"
      ]
    },
    {
      "stopName": "Poprzeczna",
      "stopLines": [
        "116",
        "124",
        "131"
      ]
    },
    {
      "stopName": "Krasickiego-Wilczyńskiego",
      "stopLines": [
        "117",
        "121",
        "126",
        "127",
        "130",
        "131",
        "141",
        "202",
        "204",
        "205",
        "303",
        "307",
        "N01",
        "Z13"
      ]
    },
    {
      "stopName": "D.H. Śliwa",
      "stopLines": [
        "117",
        "121",
        "126",
        "127",
        "130",
        "131",
        "141",
        "202",
        "204",
        "303",
        "307",
        "N01"
      ]
    },
    {
      "stopName": "Osiedle Generałów",
      "stopLines": [
        "117",
        "126",
        "141",
        "201",
        "N01"
      ]
    },
    {
      "stopName": "Janowicza",
      "stopLines": [
        "117",
        "121",
        "126",
        "127",
        "130",
        "131",
        "141",
        "202",
        "204",
        "303",
        "307",
        "N01"
      ]
    },
    {
      "stopName": "Jarocka",
      "stopLines": [
        "117",
        "121",
        "126",
        "127",
        "130",
        "131",
        "141",
        "202",
        "204",
        "303",
        "307",
        "N01"
      ]
    },
    {
      "stopName": "Bartąska",
      "stopLines": [
        "117",
        "126",
        "136",
        "141",
        "N01"
      ]
    },
    {
      "stopName": "Stalowa",
      "stopLines": [
        "121",
        "128",
        "141"
      ]
    },
    {
      "stopName": "Chłodnia Olsztyn",
      "stopLines": [
        "121",
        "128",
        "141"
      ]
    },
    {
      "stopName": "Bartąska-Rondo",
      "stopLines": [
        "121",
        "136"
      ]
    },
    {
      "stopName": "Antonowicza",
      "stopLines": [
        "121"
      ]
    },
    {
      "stopName": "Budowlana",
      "stopLines": [
        "121",
        "128",
        "141"
      ]
    },
    {
      "stopName": "Osiedle Zacisze",
      "stopLines": [
        "121",
        "136"
      ]
    },
    {
      "stopName": "Makro",
      "stopLines": [
        "121",
        "128",
        "141"
      ]
    },
    {
      "stopName": "Izba Administracji Skarbowej",
      "stopLines": [
        "121",
        "128",
        "141"
      ]
    },
    {
      "stopName": "Łęgajny-Kasztanowa",
      "stopLines": [
        "124"
      ]
    },
    {
      "stopName": "Łęgajny-Stadion",
      "stopLines": [
        "124"
      ]
    },
    {
      "stopName": "Łęgajny-Wieś",
      "stopLines": [
        "124"
      ]
    },
    {
      "stopName": "Łęgajny-Modrzewiowa",
      "stopLines": [
        "124"
      ]
    },
    {
      "stopName": "Nikielkowo",
      "stopLines": [
        "124"
      ]
    },
    {
      "stopName": "Myszki Miki",
      "stopLines": [
        "127",
        "205",
        "303",
        "307"
      ]
    },
    {
      "stopName": "Sikorskiego-Ogrody",
      "stopLines": [
        "127"
      ]
    },
    {
      "stopName": "Minakowskiego",
      "stopLines": [
        "127",
        "130",
        "131",
        "136",
        "303",
        "307",
        "N01"
      ]
    },
    {
      "stopName": "Kubusia Puchatka",
      "stopLines": [
        "127",
        "205",
        "303",
        "307",
        "N01"
      ]
    },
    {
      "stopName": "Hotel Park",
      "stopLines": [
        "128",
        "129"
      ]
    },
    {
      "stopName": "Iwaszkiewicza-Szkoła",
      "stopLines": [
        "128"
      ]
    },
    {
      "stopName": "Kalinowskiego",
      "stopLines": [
        "128"
      ]
    },
    {
      "stopName": "Gałczyńskiego",
      "stopLines": [
        "128"
      ]
    },
    {
      "stopName": "Obrońców Tobruku",
      "stopLines": [
        "128"
      ]
    },
    {
      "stopName": "Brzeziny",
      "stopLines": [
        "128"
      ]
    },
    {
      "stopName": "Wawrzyczka",
      "stopLines": [
        "128"
      ]
    },
    {
      "stopName": "Dorotowo-Rybaczówka",
      "stopLines": [
        "129"
      ]
    },
    {
      "stopName": "Dorotowo",
      "stopLines": [
        "129"
      ]
    },
    {
      "stopName": "Olsztynek-Skansen",
      "stopLines": [
        "129"
      ]
    },
    {
      "stopName": "Gryźliny-Kolonia",
      "stopLines": [
        "129"
      ]
    },
    {
      "stopName": "Zezuj",
      "stopLines": [
        "129"
      ]
    },
    {
      "stopName": "Bartąg-Kolonia",
      "stopLines": [
        "129"
      ]
    },
    {
      "stopName": "Olsztynek-Staromiejska",
      "stopLines": [
        "129"
      ]
    },
    {
      "stopName": "Dorotowo Kepijko",
      "stopLines": [
        "129"
      ]
    },
    {
      "stopName": "Stawiguda",
      "stopLines": [
        "129"
      ]
    },
    {
      "stopName": "Gryźliny",
      "stopLines": [
        "129"
      ]
    },
    {
      "stopName": "Olsztynek",
      "stopLines": [
        "129"
      ]
    },
    {
      "stopName": "Miodówko",
      "stopLines": [
        "129"
      ]
    },
    {
      "stopName": "Tomaszkowo-Miody",
      "stopLines": [
        "129"
      ]
    },
    {
      "stopName": "Tomaszkowo",
      "stopLines": [
        "129"
      ]
    },
    {
      "stopName": "Ameryka",
      "stopLines": [
        "129"
      ]
    },
    {
      "stopName": "Gryźliny-Szkoła",
      "stopLines": [
        "129"
      ]
    },
    {
      "stopName": "Rubinowa",
      "stopLines": [
        "136"
      ]
    },
    {
      "stopName": "Żelazna",
      "stopLines": [
        "141"
      ]
    },
    {
      "stopName": "Bilitewskiego",
      "stopLines": [
        "201",
        "203"
      ]
    },
    {
      "stopName": "Kutrzeby",
      "stopLines": [
        "201",
        "203"
      ]
    },
    {
      "stopName": "Kleeberga",
      "stopLines": [
        "201",
        "203"
      ]
    },
    {
      "stopName": "Popiełuszki",
      "stopLines": [
        "201",
        "203"
      ]
    },
    {
      "stopName": "Hallera",
      "stopLines": [
        "201",
        "203"
      ]
    },
    {
      "stopName": "Gębika",
      "stopLines": [
        "202",
        "204",
        "Z13"
      ]
    },
    {
      "stopName": "Pieczewo",
      "stopLines": [
        "202"
      ]
    },
    {
      "stopName": "Tęczowy Las",
      "stopLines": [
        "205"
      ]
    },
    {
      "stopName": "Wójtowa Rola-Ogrody I",
      "stopLines": [
        "304"
      ]
    },
    {
      "stopName": "Wójtowa Rola-Ogrody II",
      "stopLines": [
        "304"
      ]
    },
    {
      "stopName": "Klebark Mały-Ogrody",
      "stopLines": [
        "304"
      ]
    },
    {
      "stopName": "Świtycz-Widackiej",
      "stopLines": [
        "Z13"
      ]
    }
  ]
}